{
  "$schema": "https://developer.microsoft.com/json-schemas/fabric/item/report/definition/report/1.2.0/schema.json",
  "themeCollection": {
    "baseTheme": {
      "name": "CY24SU10",
      "reportVersionAtImport": "5.61",
      "type": "SharedResources"
    }
  },
  "layoutOptimization": "None",
  "objects": {
    "section": [
      {
        "properties": {
          "verticalAlignment": {
            "expr": {
              "Literal": {
                "Value": "'Top'"
              }
            }
          }
        }
      }
    ],
    "outspacePane": [
      {
        "properties": {
          "expanded": {
            "expr": {
              "Literal": {
                "Value": "false"
              }
            }
          }
        }
      }
    ]
  },
  "resourcePackages": [
    {
      "name": "SharedResources",
      "type": "SharedResources",
      "items": [
        {
          "name": "CY24SU10",
          "path": "BaseThemes/CY24SU10.json",
          "type": "BaseTheme"
        }
      ]
    },
    {
      "name": "RegisteredResources",
      "type": "RegisteredResources",
      "items": [
        {
          "name": "MonkeyDLuffy6132201328151057.jpg",
          "path": "MonkeyDLuffy6132201328151057.jpg",
          "type": "Image"
        },
        {
          "name": "A4_-_Poster_29945241206136535.png",
          "path": "A4_-_Poster_29945241206136535.png",
          "type": "Image"
        },
        {
          "name": "A4_-_Poster_623261002505466966.png",
          "path": "A4_-_Poster_623261002505466966.png",
          "type": "Image"
        }
      ]
    }
  ],
  "settings": {
    "useStylableVisualContainerHeader": true,
    "defaultDrillFilterOtherVisuals": true,
    "allowChangeFilterTypes": true,
    "useEnhancedTooltips": true,
    "useDefaultAggregateDisplayName": true
  }
}